{"title":"国风·唐风","uid":"8012f8a9f55b1b4022247d597928fc7e","slug":"GuoFeng_TangFeng","date":"2022-07-06T01:38:02.000Z","updated":"2022-07-20T02:49:09.210Z","comments":true,"path":"api/articles/GuoFeng_TangFeng.json","keywords":null,"cover":"https://images.pexels.com/photos/287229/pexels-photo-287229.jpeg?auto=compress&cs=tinysrgb&w=400","content":"<p>《国风·唐风》是《诗经》十五国风之一。为先秦时代唐国（晋国）民歌，有些诗以冷嘲热讽的笔调形象地揭示出奴隶主贪婪成性、不劳而获的寄生本性；有些诗写征夫思家恋土和对战争的哀怨；有些诗记叙了奴隶一年四季的劳动生活，还有不少诗表现了青年男女的爱情生活。《国风》是《诗经》的一部分。大抵是周初至春秋间各诸侯国民间诗歌。国风是《诗经》中的精华，是华夏民族文艺宝库中璀璨的明珠。</p>\n<h1 id=\"国风·唐风\"><a href=\"#国风·唐风\" class=\"headerlink\" title=\"国风·唐风\"></a>国风·唐风</h1><h3 id=\"《蟋蟀》\"><a href=\"#《蟋蟀》\" class=\"headerlink\" title=\"《蟋蟀》\"></a>《蟋蟀》</h3><p>蟋蟀在堂，岁聿其莫。今我不乐，日月其除。无已大康，职思其居。好乐无荒，良士瞿瞿。</p>\n<p>蟋蟀在堂，岁聿其逝。今我不乐，日月其迈。无已大康，职思其外。好乐无荒，良士蹶蹶。</p>\n<p>蟋蟀在堂，役车其休。今我不乐，日月其慆。无以大康。职思其忧。好乐无荒，良士休休。</p>\n<h3 id=\"《山有枢》\"><a href=\"#《山有枢》\" class=\"headerlink\" title=\"《山有枢》\"></a>《山有枢》</h3><p>山有枢，隰有榆。子有衣裳，弗曳弗娄。子有车马，弗驰弗驱。宛其死矣，他人是愉。</p>\n<p>山有栲，隰有杻。子有廷内，弗洒弗扫。子有钟鼓，弗鼓弗考。宛其死矣，他人是保。</p>\n<p>山有漆，隰有栗。子有酒食，何不日鼓瑟？且以喜乐，且以永日。宛其死矣，他人入室。</p>\n<h3 id=\"《扬之水》\"><a href=\"#《扬之水》\" class=\"headerlink\" title=\"《扬之水》\"></a>《扬之水》</h3><p>扬之水，白石凿凿。素衣朱襮，从子于沃。既见君子，云何不乐？</p>\n<p>扬之水，白石皓皓。素衣朱绣，从子于鹄。既见君子，云何其忧？</p>\n<p>扬之水，白石粼粼。我闻有命，不敢以告人。</p>\n<h3 id=\"《椒聊》\"><a href=\"#《椒聊》\" class=\"headerlink\" title=\"《椒聊》\"></a>《椒聊》</h3><p>椒聊之实，蕃衍盈升。彼其之子，硕大无朋。椒聊且，远条且。</p>\n<p>椒聊之实，蕃衍盈匊。彼其之子，硕大且笃。椒聊且，远条且。</p>\n<h3 id=\"《绸缪》\"><a href=\"#《绸缪》\" class=\"headerlink\" title=\"《绸缪》\"></a>《绸缪》</h3><p>绸缪束薪，三星在天。今夕何夕，见此良人？子兮子兮，如此良人何？</p>\n<p>绸缪束刍，三星在隅。今夕何夕，见此邂逅？子兮子兮，如此邂逅何？</p>\n<p>绸缪束楚，三星在户。今夕何夕，见此粲者？子兮子兮，如此粲者何？</p>\n<h3 id=\"《杕杜》\"><a href=\"#《杕杜》\" class=\"headerlink\" title=\"《杕杜》\"></a>《杕杜》</h3><p>有杕之杜，其叶湑湑。独行踽踽。岂无他人？不如我同父。</p>\n<p>嗟行之人，胡不比焉？人无兄弟，胡不佽焉？</p>\n<p>有杕之杜，其叶箐箐。独行 。岂无他人？不如我同姓。</p>\n<p>嗟行之人，胡不比焉？人无兄弟，胡不佽焉？</p>\n<h3 id=\"《羔裘》\"><a href=\"#《羔裘》\" class=\"headerlink\" title=\"《羔裘》\"></a>《羔裘》</h3><p>羔裘豹祛，自我人居居。岂无他人？维子之故。</p>\n<p>羔裘豹褎，自我人究究。岂无他人？维子之好。</p>\n<h3 id=\"《鸨羽》\"><a href=\"#《鸨羽》\" class=\"headerlink\" title=\"《鸨羽》\"></a>《鸨羽》</h3><p>肃肃鸨羽，集于苞栩。王事靡盬，不能蓺稷黍。父母何怙？悠悠苍天，曷其有所？</p>\n<p>肃肃鸨翼，集于苞棘。王事靡盬，不能蓺黍稷。父母何食？悠悠苍天，曷其有极？</p>\n<p>肃肃鸨行，集于苞桑，王事靡盬，不能蓺稻梁。父母何尝？悠悠苍天，曷其有常？</p>\n<h3 id=\"《无衣》\"><a href=\"#《无衣》\" class=\"headerlink\" title=\"《无衣》\"></a>《无衣》</h3><p>岂曰无衣七兮？不如子之衣，安且吉兮！</p>\n<p>岂曰无衣六兮？不如子之衣，安且燠兮！</p>\n<h3 id=\"《有杕之杜》\"><a href=\"#《有杕之杜》\" class=\"headerlink\" title=\"《有杕之杜》\"></a>《有杕之杜》</h3><p>有杕之杜，生于道左。彼君子兮，噬肯适我？中心好之，曷饮食之？</p>\n<p>有杕之杜，生于道周。彼君子兮，噬肯来游？中心好之，曷饮食之？</p>\n<h3 id=\"《葛生》\"><a href=\"#《葛生》\" class=\"headerlink\" title=\"《葛生》\"></a>《葛生》</h3><p>葛生蒙楚，蔹蔓于野。予美亡此，谁与？独处？</p>\n<p>葛生蒙棘，蔹蔓于域。予美亡此，谁与？独息？</p>\n<p>角枕粲兮，锦衾烂兮。予美亡此，谁与？独旦？</p>\n<p>夏之日，冬之夜。百岁之后，归于其居。</p>\n<p>冬之夜，夏之日。百岁之后，归于其室。</p>\n<h3 id=\"《采苓》\"><a href=\"#《采苓》\" class=\"headerlink\" title=\"《采苓》\"></a>《采苓》</h3><p>采苓采苓，首阳之巅。人之为言，苟亦无信。舍旃舍旃，苟亦无然。人之为言，胡得焉？</p>\n<p>采苦采苦，首阳之下。人之为言，苟亦无与。舍旃舍旃，苟亦无然。人之为言，胡得焉？</p>\n<p>采葑采葑，首阳之东。人之为言，苟亦无从。舍旃舍旃，苟亦无然。人之为言，胡得焉？</p>\n","text":"《国风·唐风》是《诗经》十五国风之一。为先秦时代唐国（晋国）民歌，有些诗以冷嘲热讽的笔调形象地揭示出奴隶主贪婪成性、不劳而获的寄生本性；有些诗写征夫思家恋土和对战争的哀怨；有些诗记叙了奴隶一年四季的劳动生活，还有不少诗表现了青年男女的爱情生活。《国风》是《诗经》的一部分。大抵是周...","link":"","photos":[],"count_time":{"symbolsCount":"1.3k","symbolsTime":"1 mins."},"categories":[{"name":"国风","slug":"国风","count":15,"path":"api/categories/国风.json"}],"tags":[{"name":"诗经","slug":"诗经","count":15,"path":"api/tags/诗经.json"},{"name":"国风","slug":"国风","count":15,"path":"api/tags/国风.json"}],"toc":"<ol class=\"toc\"><li class=\"toc-item toc-level-1\"><a class=\"toc-link\" href=\"#%E5%9B%BD%E9%A3%8E%C2%B7%E5%94%90%E9%A3%8E\"><span class=\"toc-text\">国风·唐风</span></a><ol class=\"toc-child\"><li class=\"toc-item toc-level-3\"><a class=\"toc-link\" href=\"#%E3%80%8A%E8%9F%8B%E8%9F%80%E3%80%8B\"><span class=\"toc-text\">《蟋蟀》</span></a></li><li class=\"toc-item toc-level-3\"><a class=\"toc-link\" href=\"#%E3%80%8A%E5%B1%B1%E6%9C%89%E6%9E%A2%E3%80%8B\"><span class=\"toc-text\">《山有枢》</span></a></li><li class=\"toc-item toc-level-3\"><a class=\"toc-link\" href=\"#%E3%80%8A%E6%89%AC%E4%B9%8B%E6%B0%B4%E3%80%8B\"><span class=\"toc-text\">《扬之水》</span></a></li><li class=\"toc-item toc-level-3\"><a class=\"toc-link\" href=\"#%E3%80%8A%E6%A4%92%E8%81%8A%E3%80%8B\"><span class=\"toc-text\">《椒聊》</span></a></li><li class=\"toc-item toc-level-3\"><a class=\"toc-link\" href=\"#%E3%80%8A%E7%BB%B8%E7%BC%AA%E3%80%8B\"><span class=\"toc-text\">《绸缪》</span></a></li><li class=\"toc-item toc-level-3\"><a class=\"toc-link\" href=\"#%E3%80%8A%E6%9D%95%E6%9D%9C%E3%80%8B\"><span class=\"toc-text\">《杕杜》</span></a></li><li class=\"toc-item toc-level-3\"><a class=\"toc-link\" href=\"#%E3%80%8A%E7%BE%94%E8%A3%98%E3%80%8B\"><span class=\"toc-text\">《羔裘》</span></a></li><li class=\"toc-item toc-level-3\"><a class=\"toc-link\" href=\"#%E3%80%8A%E9%B8%A8%E7%BE%BD%E3%80%8B\"><span class=\"toc-text\">《鸨羽》</span></a></li><li class=\"toc-item toc-level-3\"><a class=\"toc-link\" href=\"#%E3%80%8A%E6%97%A0%E8%A1%A3%E3%80%8B\"><span class=\"toc-text\">《无衣》</span></a></li><li class=\"toc-item toc-level-3\"><a class=\"toc-link\" href=\"#%E3%80%8A%E6%9C%89%E6%9D%95%E4%B9%8B%E6%9D%9C%E3%80%8B\"><span class=\"toc-text\">《有杕之杜》</span></a></li><li class=\"toc-item toc-level-3\"><a class=\"toc-link\" href=\"#%E3%80%8A%E8%91%9B%E7%94%9F%E3%80%8B\"><span class=\"toc-text\">《葛生》</span></a></li><li class=\"toc-item toc-level-3\"><a class=\"toc-link\" href=\"#%E3%80%8A%E9%87%87%E8%8B%93%E3%80%8B\"><span class=\"toc-text\">《采苓》</span></a></li></ol></li></ol></li></ol>","author":{"name":"ORLA","slug":"blog-author","avatar":"https://s3.bmp.ovh/imgs/2022/07/05/f30c5a60868494ae.png","link":"/","description":"LIFE AND DREAM","socials":{"github":"https://github.com","twitter":"","stackoverflow":"","wechat":"","qq":"","weibo":"https://weibo.com","zhihu":"https://www.zhihu.com","csdn":"https://csdn.net","juejin":"","customs":{}}},"mapped":true,"prev_post":{"title":"国风·陈风","uid":"2e33c57e3f37b42f4b3ab2a097bff133","slug":"GuoFeng_ChenFeng","date":"2022-07-06T01:38:02.000Z","updated":"2022-07-20T02:49:14.578Z","comments":true,"path":"api/articles/GuoFeng_ChenFeng.json","keywords":null,"cover":"https://images.pexels.com/photos/991422/pexels-photo-991422.jpeg?auto=compress&cs=tinysrgb&w=400","text":"《国风·陈风》，是《诗经》十五国风之一，共10篇。《国风》是《诗经》的一部分。大抵是周初至春秋间各诸侯国民间诗歌。国风是《诗经》中的精华，是华夏民族文艺宝库中璀璨的明珠。 国风·陈风《宛丘》子之汤兮，宛丘之上兮。洵有情兮，而无望兮。 坎其击鼓，宛丘之下。无冬无夏，值其鹭羽。 坎其...","link":"","photos":[],"count_time":{"symbolsCount":737,"symbolsTime":"1 mins."},"categories":[{"name":"国风","slug":"国风","count":15,"path":"api/categories/国风.json"}],"tags":[{"name":"诗经","slug":"诗经","count":15,"path":"api/tags/诗经.json"},{"name":"国风","slug":"国风","count":15,"path":"api/tags/国风.json"}],"author":{"name":"ORLA","slug":"blog-author","avatar":"https://s3.bmp.ovh/imgs/2022/07/05/f30c5a60868494ae.png","link":"/","description":"LIFE AND DREAM","socials":{"github":"https://github.com","twitter":"","stackoverflow":"","wechat":"","qq":"","weibo":"https://weibo.com","zhihu":"https://www.zhihu.com","csdn":"https://csdn.net","juejin":"","customs":{}}}},"next_post":{"title":"国风·鄘风","uid":"05abe0d0b7acbdb78b827dce6cc765d5","slug":"GuoFeng_YongFeng","date":"2022-07-06T01:38:02.000Z","updated":"2022-07-20T02:49:09.323Z","comments":true,"path":"api/articles/GuoFeng_YongFeng.json","keywords":null,"cover":"https://images.pexels.com/photos/355747/pexels-photo-355747.jpeg?auto=compress&cs=tinysrgb&w=1260&h=750&dpr=1","text":"《鄘风》为鄘地华夏族民歌。周武王克商，分商都朝歌以北为邶，南为鄘，东为卫。故地在今河南省卫辉市境内。《国风》是《诗经》的一部分。大抵是周初至春秋间各诸侯国民间诗歌。国风是《诗经》中的精华，是华夏民族文艺宝库中璀璨的明珠。 国风·鄘风《柏舟》泛彼柏舟，在彼中河。髧彼两髦，实维我仪。...","link":"","photos":[],"count_time":{"symbolsCount":"1.1k","symbolsTime":"1 mins."},"categories":[{"name":"国风","slug":"国风","count":15,"path":"api/categories/国风.json"}],"tags":[{"name":"诗经","slug":"诗经","count":15,"path":"api/tags/诗经.json"},{"name":"国风","slug":"国风","count":15,"path":"api/tags/国风.json"}],"author":{"name":"ORLA","slug":"blog-author","avatar":"https://s3.bmp.ovh/imgs/2022/07/05/f30c5a60868494ae.png","link":"/","description":"LIFE AND DREAM","socials":{"github":"https://github.com","twitter":"","stackoverflow":"","wechat":"","qq":"","weibo":"https://weibo.com","zhihu":"https://www.zhihu.com","csdn":"https://csdn.net","juejin":"","customs":{}}}}}