{"title":"国风·卫风","uid":"ef0bbbc657fbe1599e9df607617270c3","slug":"GuoFeng_WeiFeng1","date":"2022-07-08T05:46:44.000Z","updated":"2022-07-20T07:00:38.495Z","comments":false,"path":"api/articles/GuoFeng_WeiFeng1.json","keywords":null,"cover":"https://images.pexels.com/photos/4215100/pexels-photo-4215100.jpeg?auto=compress&cs=tinysrgb&w=1260&h=750&dpr=1","content":"<p>《国风·卫风》，《诗经》篇章之总名。十五国风之一。共十篇。先秦时代卫国地方民歌。《国风》是《诗经》的一部分。大抵是周初至春秋间各诸侯国民间诗歌。国风是《诗经》中的精华，是华夏民族文艺宝库中璀璨的明珠。</p>\n<h1 id=\"国风·卫风\"><a href=\"#国风·卫风\" class=\"headerlink\" title=\"国风·卫风\"></a>国风·卫风</h1><h3 id=\"《淇奥》\"><a href=\"#《淇奥》\" class=\"headerlink\" title=\"《淇奥》\"></a>《淇奥》</h3><p>瞻彼淇奥，绿竹猗猗。有匪君子，如切如磋，如琢如磨，瑟兮僴兮，赫兮咺兮。有匪君子，终不可谖兮。</p>\n<p>瞻彼淇奥，绿竹青青。有匪君子，充耳 秀莹，会弁如星。瑟兮僴兮。赫兮咺兮，有匪君子，终不可谖兮。</p>\n<p>瞻彼淇奥，绿竹如箦。有匪君子，如金如锡，如圭如璧。宽兮绰兮，猗重较兮。善戏谑兮，不为虐兮。</p>\n<h3 id=\"《考槃》\"><a href=\"#《考槃》\" class=\"headerlink\" title=\"《考槃》\"></a>《考槃》</h3><p>考槃在涧，硕人之宽。独寐寤言，永矢弗谖。</p>\n<p>考槃在阿，硕人之薖。独寐寤歌，永矢弗过。</p>\n<p>考槃在陆，硕人之轴。独寐寤宿，永矢弗告。</p>\n<h3 id=\"《硕人》\"><a href=\"#《硕人》\" class=\"headerlink\" title=\"《硕人》\"></a>《硕人》</h3><p>硕人其颀，衣锦褧衣。齐侯之子，卫侯之妻。东宫之妹，邢侯之姨，谭公维私。</p>\n<p>手如柔荑，肤如凝脂，领如蝤蛴，齿如瓠犀，螓首蛾眉，巧笑倩兮，美目盼兮。</p>\n<p>硕人敖敖，说于农郊。四牡有骄，朱幩镳镳。翟茀以朝。大夫夙退，无使君劳。</p>\n<p>河水洋洋，北流活活。施罛濊濊，鳣鲔发发。葭菼揭揭，庶姜孽孽，庶士有朅。</p>\n<h3 id=\"《氓》\"><a href=\"#《氓》\" class=\"headerlink\" title=\"《氓》\"></a>《氓》</h3><p>氓之蚩蚩，抱布贸丝。匪来贸丝，来即我谋。送子涉淇，至于顿丘。匪我愆期，子无良媒。将子无怒，秋以为期。</p>\n<p>乘彼垝垣，以望复关。不见复关，泣涕涟涟。既见复关，载笑载言。尔卜尔筮，体无咎言。以尔车来，以我贿迁。</p>\n<p>桑之未落，其叶沃若。于嗟鸠兮！无食桑葚。于嗟女兮！无与士耽。士之耽兮，犹可说也。女之耽兮，不可说也。</p>\n<p>桑之落矣，其黄而陨。自我徂尔，三岁食贫。淇水汤汤，渐车帷裳。女也不爽，士贰其行。士也罔极，二三其德。</p>\n<p>三岁为妇，靡室劳矣。夙兴夜寐，靡有朝矣 。言既遂矣，至于暴矣。兄弟不知，咥其笑矣。静言思之，躬自悼矣。</p>\n<p>及尔偕老，老使我怨。淇则有岸，隰则有泮。总角之宴，言笑晏晏，信誓旦旦，不思其反。反是不思，亦已焉哉！</p>\n<h3 id=\"《竹竿》\"><a href=\"#《竹竿》\" class=\"headerlink\" title=\"《竹竿》\"></a>《竹竿》</h3><p>籊籊竹竿，以钓于淇。岂不尔思？远莫致之。</p>\n<p>泉源在左，淇水在右。女子有行，远兄弟父母。</p>\n<p>淇水在右，泉源在左。巧笑之瑳，佩玉之傩。</p>\n<p>淇水滺滺，桧楫松舟。驾言出游，以写我忧。</p>\n<h3 id=\"《芄兰》\"><a href=\"#《芄兰》\" class=\"headerlink\" title=\"《芄兰》\"></a>《芄兰》</h3><p>芄兰之支 ，童子佩觿。虽则佩觿，能不我知。容兮遂兮，垂带悸兮。</p>\n<p>芄兰之叶，童子佩韘。虽则佩韘，能不我甲。容兮遂兮，垂带悸兮。</p>\n<h3 id=\"《河广》\"><a href=\"#《河广》\" class=\"headerlink\" title=\"《河广》\"></a>《河广》</h3><p>谁谓河广？一苇杭之。谁谓宋远？跂予望之。</p>\n<p>谁谓河广？曾不容刀。谁谓宋远？曾不崇朝。</p>\n<h3 id=\"《伯兮》\"><a href=\"#《伯兮》\" class=\"headerlink\" title=\"《伯兮》\"></a>《伯兮》</h3><p>伯兮朅兮，邦之桀兮。伯也执殳，为王前驱。</p>\n<p>自伯之东，首如飞蓬。岂无膏沐？谁适为容！</p>\n<p>其雨其雨，杲杲出日。愿言思伯，甘心首疾。</p>\n<p>焉得谖草？言树之背。愿言思伯。使我心痗。</p>\n<h3 id=\"《有狐》\"><a href=\"#《有狐》\" class=\"headerlink\" title=\"《有狐》\"></a>《有狐》</h3><p>有狐绥绥，在彼淇梁。心之忧矣，之子无裳。</p>\n<p>有狐绥绥，在彼淇厉。心之忧矣，之子无带。</p>\n<p>有狐绥绥，在彼淇侧。心之忧矣，之子无服。</p>\n<h3 id=\"《木瓜》\"><a href=\"#《木瓜》\" class=\"headerlink\" title=\"《木瓜》\"></a>《木瓜》</h3><p>投我以木瓜，报之以琼琚。匪报也，永以为好也！</p>\n<p>投我以木桃，报之以琼瑶。匪报也，永以为好也！</p>\n<p>投我以木李，报之以琼玖。匪报也，永以为好也！</p>\n","feature":true,"text":"《国风·卫风》，《诗经》篇章之总名。十五国风之一。共十篇。先秦时代卫国地方民歌。《国风》是《诗经》的一部分。大抵是周初至春秋间各诸侯国民间诗歌。国风是《诗经》中的精华，是华夏民族文艺宝库中璀璨的明珠。 国风·卫风《淇奥》瞻彼淇奥，绿竹猗猗。有匪君子，如切如磋，如琢如磨，瑟兮僴兮，...","link":"","photos":[],"count_time":{"symbolsCount":"1.2k","symbolsTime":"1 mins."},"categories":[{"name":"国风","slug":"国风","count":15,"path":"api/categories/国风.json"}],"tags":[{"name":"诗经","slug":"诗经","count":15,"path":"api/tags/诗经.json"},{"name":"国风","slug":"国风","count":15,"path":"api/tags/国风.json"}],"toc":"<ol class=\"toc\"><li class=\"toc-item toc-level-1\"><a class=\"toc-link\" href=\"#%E5%9B%BD%E9%A3%8E%C2%B7%E5%8D%AB%E9%A3%8E\"><span class=\"toc-text\">国风·卫风</span></a><ol class=\"toc-child\"><li class=\"toc-item toc-level-3\"><a class=\"toc-link\" href=\"#%E3%80%8A%E6%B7%87%E5%A5%A5%E3%80%8B\"><span class=\"toc-text\">《淇奥》</span></a></li><li class=\"toc-item toc-level-3\"><a class=\"toc-link\" href=\"#%E3%80%8A%E8%80%83%E6%A7%83%E3%80%8B\"><span class=\"toc-text\">《考槃》</span></a></li><li class=\"toc-item toc-level-3\"><a class=\"toc-link\" href=\"#%E3%80%8A%E7%A1%95%E4%BA%BA%E3%80%8B\"><span class=\"toc-text\">《硕人》</span></a></li><li class=\"toc-item toc-level-3\"><a class=\"toc-link\" href=\"#%E3%80%8A%E6%B0%93%E3%80%8B\"><span class=\"toc-text\">《氓》</span></a></li><li class=\"toc-item toc-level-3\"><a class=\"toc-link\" href=\"#%E3%80%8A%E7%AB%B9%E7%AB%BF%E3%80%8B\"><span class=\"toc-text\">《竹竿》</span></a></li><li class=\"toc-item toc-level-3\"><a class=\"toc-link\" href=\"#%E3%80%8A%E8%8A%84%E5%85%B0%E3%80%8B\"><span class=\"toc-text\">《芄兰》</span></a></li><li class=\"toc-item toc-level-3\"><a class=\"toc-link\" href=\"#%E3%80%8A%E6%B2%B3%E5%B9%BF%E3%80%8B\"><span class=\"toc-text\">《河广》</span></a></li><li class=\"toc-item toc-level-3\"><a class=\"toc-link\" href=\"#%E3%80%8A%E4%BC%AF%E5%85%AE%E3%80%8B\"><span class=\"toc-text\">《伯兮》</span></a></li><li class=\"toc-item toc-level-3\"><a class=\"toc-link\" href=\"#%E3%80%8A%E6%9C%89%E7%8B%90%E3%80%8B\"><span class=\"toc-text\">《有狐》</span></a></li><li class=\"toc-item toc-level-3\"><a class=\"toc-link\" href=\"#%E3%80%8A%E6%9C%A8%E7%93%9C%E3%80%8B\"><span class=\"toc-text\">《木瓜》</span></a></li></ol></li></ol></li></ol>","author":{"name":"ORLA","slug":"blog-author","avatar":"https://s3.bmp.ovh/imgs/2022/07/05/f30c5a60868494ae.png","link":"/","description":"LIFE AND DREAM","socials":{"github":"https://github.com","twitter":"","stackoverflow":"","wechat":"","qq":"","weibo":"https://weibo.com","zhihu":"https://www.zhihu.com","csdn":"https://csdn.net","juejin":"","customs":{}}},"mapped":true,"prev_post":{"title":"国风·王风","uid":"6ffb0108ad84dc998ddf3ff03870cd96","slug":"GuoFeng_WangFeng","date":"2022-07-08T07:54:38.000Z","updated":"2022-07-20T07:02:48.860Z","comments":true,"path":"api/articles/GuoFeng_WangFeng.json","keywords":null,"cover":"https://images.pexels.com/photos/2365457/pexels-photo-2365457.jpeg?auto=compress&cs=tinysrgb&w=1260&h=750&dpr=1","text":"《国风·王风》，是《诗经》十五国风之一，共十篇。《国风》是《诗经》的一部分。大抵是周初至春秋间各诸侯国民间诗歌。国风是《诗经》中的精华，是华夏民族文艺宝库中璀璨的明珠。 国风·王风《黍离》彼黍离离，彼稷之苗。行迈靡靡，中心摇摇。知我者，谓我心忧；不知我者，谓我何求。悠悠苍天，此何...","link":"","photos":[],"count_time":{"symbolsCount":978,"symbolsTime":"1 mins."},"categories":[{"name":"国风","slug":"国风","count":15,"path":"api/categories/国风.json"}],"tags":[{"name":"诗经","slug":"诗经","count":15,"path":"api/tags/诗经.json"},{"name":"国风","slug":"国风","count":15,"path":"api/tags/国风.json"}],"author":{"name":"ORLA","slug":"blog-author","avatar":"https://s3.bmp.ovh/imgs/2022/07/05/f30c5a60868494ae.png","link":"/","description":"LIFE AND DREAM","socials":{"github":"https://github.com","twitter":"","stackoverflow":"","wechat":"","qq":"","weibo":"https://weibo.com","zhihu":"https://www.zhihu.com","csdn":"https://csdn.net","juejin":"","customs":{}}},"feature":true},"next_post":{"title":"国风·豳风","uid":"1d605989dc185efdc15c5f0d41581277","slug":"GuoFeng_BinFeng","date":"2022-07-06T01:38:02.000Z","updated":"2022-07-20T02:49:12.262Z","comments":true,"path":"api/articles/GuoFeng_BinFeng.json","keywords":null,"cover":"https://images.pexels.com/photos/1785493/pexels-photo-1785493.jpeg?auto=compress&cs=tinysrgb&w=400","text":"豳（音bīn）风，是《诗经》十五国风之一。共七篇，为先秦时代豳地华夏族民歌。豳同邠，古都邑名，在今甘肃庆阳、陕西旬邑、彬县一带，是周族部落的发祥地。《国风》是《诗经》的一部分。大抵是周初至春秋间各诸侯国民间诗歌。国风是《诗经》中的精华，是华夏民族文艺宝库中璀璨的明珠。 国风·豳风...","link":"","photos":[],"count_time":{"symbolsCount":"1.3k","symbolsTime":"1 mins."},"categories":[{"name":"国风","slug":"国风","count":15,"path":"api/categories/国风.json"}],"tags":[{"name":"诗经","slug":"诗经","count":15,"path":"api/tags/诗经.json"},{"name":"国风","slug":"国风","count":15,"path":"api/tags/国风.json"}],"author":{"name":"ORLA","slug":"blog-author","avatar":"https://s3.bmp.ovh/imgs/2022/07/05/f30c5a60868494ae.png","link":"/","description":"LIFE AND DREAM","socials":{"github":"https://github.com","twitter":"","stackoverflow":"","wechat":"","qq":"","weibo":"https://weibo.com","zhihu":"https://www.zhihu.com","csdn":"https://csdn.net","juejin":"","customs":{}}},"feature":true}}